[
    {
        "id": "84d37a94fed2ef76",
        "type": "ui_chart",
        "z": "f8bbc79e19e01d7a",
        "name": "",
        "group": "09c3b871948949d6",
        "order": 3,
        "width": 0,
        "height": 0,
        "label": "Historico local",
        "chartType": "line",
        "legend": "false",
        "xformat": "HH:mm:ss",
        "interpolate": "linear",
        "nodata": "",
        "dot": false,
        "ymin": "0",
        "ymax": "100",
        "removeOlder": "20",
        "removeOlderPoints": "",
        "removeOlderUnit": "60",
        "cutout": 0,
        "useOneColor": false,
        "useUTC": false,
        "colors": [
            "#1f77b4",
            "#aec7e8",
            "#ff7f0e",
            "#2ca02c",
            "#98df8a",
            "#d62728",
            "#ff9896",
            "#9467bd",
            "#c5b0d5"
        ],
        "outputs": 1,
        "useDifferentColor": false,
        "className": "",
        "x": 640,
        "y": 240,
        "wires": [
            []
        ]
    },
    {
        "id": "09c3b871948949d6",
        "type": "ui_group",
        "name": "Informacion por MQTT",
        "tab": "b816344434f132e1",
        "order": 1,
        "disp": true,
        "width": "12",
        "collapse": false,
        "className": ""
    },
    {
        "id": "b816344434f132e1",
        "type": "ui_tab",
        "name": "Flow5-Clima por API",
        "icon": "dashboard",
        "order": 3,
        "disabled": false,
        "hidden": false
    }
]